beamz/README.md
beamz/__init__.py
beamz/const.py
beamz/design/README.md
beamz/design/__init__.py
beamz/design/core.py
beamz/design/io.py
beamz/design/library.py
beamz/design/materials.py
beamz/design/meshing.py
beamz/design/structures.py
beamz/devices/README.md
beamz/devices/__init__.py
beamz/devices/core.py
beamz/devices/monitors/README.md
beamz/devices/monitors/__init__.py
beamz/devices/monitors/monitors.py
beamz/devices/sources/__init__.py
beamz/devices/sources/gaussian.py
beamz/devices/sources/jax_utils.py
beamz/devices/sources/mode.py
beamz/devices/sources/signals.py
beamz/devices/sources/solve.py
beamz/optimization/README.md
beamz/optimization/__init__.py
beamz/optimization/autodiff.py
beamz/optimization/topology.py
beamz/simulation/README.md
beamz/simulation/__init__.py
beamz/simulation/boundaries.py
beamz/simulation/core.py
beamz/simulation/fields.py
beamz/simulation/ops.py
beamz/visual/README.md
beamz/visual/__init__.py
beamz/visual/core.py
beamz/visual/helpers.py
beamz/visual/viz.py
beamz-0.1.20.dist-info/METADATA
beamz-0.1.20.dist-info/WHEEL
beamz-0.1.20.dist-info/licenses/LICENSE
beamz-0.1.20.dist-info/RECORD
