Metadata-Version: 2.4
Name: beamz
Version: 0.1.20
Summary: EM package to create inverse / generative designs for your photonic devices with ease and efficiency.
Project-URL: Homepage, https://github.com/QuentinWach/beamz
Project-URL: Repository, https://github.com/QuentinWach/beamz
Author-email: Quentin Wach <quentin.wach+beamz@gmail.com>
License: Copyright © 2025 Quentin Wach
License-File: LICENSE
Keywords: electromagnetics,generative design,inverse design,photonics,simulation
Classifier: Development Status :: 3 - Alpha
Classifier: Intended Audience :: Science/Research
Classifier: Operating System :: OS Independent
Classifier: Programming Language :: Python :: 3
Classifier: Programming Language :: Python :: 3.10
Classifier: Programming Language :: Python :: 3.11
Classifier: Programming Language :: Python :: 3.12
Classifier: Topic :: Scientific/Engineering :: Physics
Requires-Python: >=3.10
Requires-Dist: gdspy>=1.6.0
Requires-Dist: jax>=0.4.0
Requires-Dist: jaxlib>=0.4.0
Requires-Dist: matplotlib>=3.7.5
Requires-Dist: numpy>=1.24.4
Requires-Dist: optax>=0.1.0
Requires-Dist: rich>=13.9.4
Requires-Dist: scipy>=1.10.1
Requires-Dist: shapely>=2.0.6
Provides-Extra: dev
Requires-Dist: black>=22.0.0; extra == 'dev'
Requires-Dist: flake8>=4.0.0; extra == 'dev'
Requires-Dist: isort>=5.0.0; extra == 'dev'
Requires-Dist: mkdocs-material>=9.0.0; extra == 'dev'
Requires-Dist: mkdocs>=1.5.0; extra == 'dev'
Requires-Dist: myst-parser>=2.0.0; extra == 'dev'
Requires-Dist: pytest-cov>=4.0.0; extra == 'dev'
Requires-Dist: pytest>=7.0.0; extra == 'dev'
Provides-Extra: gpu
Requires-Dist: torch>=2.6.0; extra == 'gpu'
Provides-Extra: test
Requires-Dist: pytest-cov>=4.0.0; extra == 'test'
Requires-Dist: pytest-randomly>=3.0.0; extra == 'test'
Requires-Dist: pytest>=7.0.0; extra == 'test'
Requires-Dist: tidy3d>=2.0.0; extra == 'test'
